gapy/__init__.py
gapy/gapy.py
gapy/gapy2.py
gapy/tools.py
genapy-0.0.13.dist-info/LICENSE
genapy-0.0.13.dist-info/METADATA
genapy-0.0.13.dist-info/WHEEL
genapy-0.0.13.dist-info/top_level.txt
genapy-0.0.13.dist-info/RECORD
