Metadata-Version: 2.1
Name: genapy
Version: 0.0.13
Summary: Genetic Algorithm for Python
Home-page: https://github.com/fotobiolab-unb/gapy
Author: Icaro Lorran Lopes Costa
Author-email: icarosadero@gmail.com
License: GPL-3
Project-URL: Bug Tracker, https://github.com/fotobiolab-unb/gapy/issues
Platform: UNKNOWN
Classifier: Programming Language :: Python :: 3
Classifier: License :: OSI Approved :: GNU General Public License v3 or later (GPLv3+)
Classifier: Operating System :: OS Independent
Requires-Python: >=3.6
License-File: LICENSE
